obs/__init__.py
obs/auth.py
obs/bucket.py
obs/bulktasks.py
obs/cache.py
obs/client.py
obs/const.py
obs/convertor.py
obs/crypto_client.py
obs/extension.py
obs/http2.py
obs/ilog.py
obs/loadtoken.py
obs/locks.py
obs/model.py
obs/obs_cipher_suite.py
obs/posix_transfer.py
obs/progress.py
obs/searchmethod.py
obs/transfer.py
obs/util.py
obs/workflow.py
esdk_obs_python_makus-3.23.12.dist-info/METADATA
esdk_obs_python_makus-3.23.12.dist-info/WHEEL
esdk_obs_python_makus-3.23.12.dist-info/top_level.txt
esdk_obs_python_makus-3.23.12.dist-info/RECORD
